sauce/__init__.py
sauce/imagenet/__init__.py
sauce/imagenet/imagenet.py
sauce/nltkrdf/__init__.py
sauce/nltkrdf/wordnet.py
sauce_lib_nltk-16.0.0.dist-info/LICENSE
sauce_lib_nltk-16.0.0.dist-info/METADATA
sauce_lib_nltk-16.0.0.dist-info/WHEEL
sauce_lib_nltk-16.0.0.dist-info/top_level.txt
sauce_lib_nltk-16.0.0.dist-info/RECORD
