Metadata-Version: 2.1
Name: sauce-lib-nltk
Version: 16.0.0
Summary: gets synonyms and hypernyms of labels for an asset
Home-page: UNKNOWN
Author: William Greenly
Author-email: wmg@dneg.com
License: UNKNOWN
Platform: UNKNOWN
Classifier: Programming Language :: Python :: 3
Classifier: License :: OSI Approved :: MIT License
Classifier: Operating System :: OS Independent
Requires-Python: >=3.6
Requires-Dist: nltk
Requires-Dist: rdflib
Requires-Dist: rdflib-jsonld
Requires-Dist: requests
Requires-Dist: twine
Requires-Dist: inflect
